{"type":{"type":"youtube","data":{"item":{"url":"https://youtu.be/W14a0gqE1B8?si=3GWx3iXrD-r8tWde","title":"مقطع رائع عن حياة الأنسان القصيرة وكيفية الإستفادة منها للنجاة من العذاب يوم القيامة","addedAt":"2025-04-25T05:26:53.694938","thumbnailUrl":"https://img.youtube.com/vi/W14a0gqE1B8/hqdefault.jpg","channel":{"channelId":"UCNxth2zrPsUqwp4PDnsVhPw","title":"إسلاميات","logoUrl":"https://yt3.googleusercontent.com/ggAGgOpGDeFA4jW7TVYlpRDejbExfP5AfDx_jNWsiasmuvMMHouOzgqc1JIgRl9B6B11wnXHxw=s900-c-k-c0x00ffffff-no-rj","bannerUrl":"","subscribersCount":null}}}},"groups":["-OJerXriuyTTb69CMTC5"],"collections":["main","-OJerXvKCplUUx-ptcKN"],"title":{"translations":{"en":"مقطع رائع عن حياة الأنسان القصيرة وكيفية الاستفادة منها للنجاة من العذاب يوم القيامة"}},"description":{"translations":{"en":""}},"createdAt":"2025-04-25T05:26:53.694977","updatedAt":"2025-04-25T05:26:53.694978","createdBy":{"email":"sha.kamel.eng@gmail.com","id":"7rD1JGJZ7Eg9nWzIYySMucJJqkv2","isAdmin":true},"isPromoted":false,"id":"cooknujjtjpopiX_jMloWkbl4l1szndxn6MsndNm3hmsoMZ_"}