{"type":{"type":"archive","data":{"item":{"type":{"type":"item","data":{"metadata":{"identifier":"006_20210914","mediatype":"audio","description":"","title":"","publicdate":"2021-09-14T20:28:20.000","addeddate":"2021-09-14T20:28:20.000"}}}}}},"groups":["-OJerXriuyTTb69CMTBr"],"collections":["main","-OJerXvKCplUUx-ptcKN"],"title":{"translations":{"ar":"شرح البلاغة من كتاب قواعد اللغة العربية {الشرح الأول} سماحة الشيخ العلامة محمد بن صالح العثيمين"}},"description":{"translations":{"ar":"قناة خزائن الرحمن على اليوتيوب"}},"createdAt":"2025-02-21T11:45:37.902570","updatedAt":"2025-02-21T11:45:37.902575","createdBy":{"email":"sha.kamel.eng@gmail.com","id":"7rD1JGJZ7Eg9nWzIYySMucJJqkv2","isAdmin":true},"isPromoted":false,"id":"cooknujjWmYcdq_ijmbjZ_oWdgnjkkqUmkmlktlo"}